{
  "app_name": "My App",
  "menu_home": "Home",
  "menu_about": "About",
  "menu_tokens": "Tokens",
  "menu_contact": "Contact",
  "menu_connect": "Connect",
  "right_menu_referrals": "My Referrals",
  "right_menu_marketplaces": "Marketplaces",
  "home_title": "Welcome to the Home Page",
  "home_first_paragraph": "EN Lorem ipsum dolor sit amet, consectetur adipiscing elit. Integer pellentesque tellus ac libero euismod, at maximus justo cursus. Nulla a euismod nunc, sit amet tincidunt ante. Etiam commodo, risus ut sagittis luctus, mauris purus lobortis neque, ut molestie mauris purus a dui. Vestibulum vulputate lorem ut libero laoreet auctor. Integer in euismod purus, nec interdum sapien. Donec sed commodo turpis. Quisque condimentum vulputate mattis. Cras a enim et justo fermentum ornare tempus eu augue. Integer augue eros, fringilla sit amet euismod sed, dictum in arcu.",
  "home_second_paragraph": "EN Lorem ipsum dolor sit amet, consectetur adipiscing elit. Integer pellentesque tellus ac libero euismod, at maximus justo cursus. Nulla a euismod nunc, sit amet tincidunt ante. Etiam commodo, risus ut sagittis luctus, mauris purus lobortis neque, ut molestie mauris purus a dui. Vestibulum vulputate lorem ut libero laoreet auctor. Integer in euismod purus, nec interdum sapien. Donec sed commodo turpis. Quisque condimentum vulputate mattis. Cras a enim et justo fermentum ornare tempus eu augue. Integer augue eros, fringilla sit amet euismod sed, dictum in arcu.",
  "about_title": "About Us",
  "contact_title": "Contact Us",
  "referrals_title": "Referrals",
  "marketplaces_title": "Marketplaces"
}
